[
  {
    "file_name": "photo-1583620429827-d25b34ffcd90",
    "url": "https://images.unsplash.com/photo-1583620429827-d25b34ffcd90?ixlib=rb-1.2.1&q=80&fm=jpg&crop=entropy&cs=tinysrgb&w=1080&fit=max",
    "file_size": 137026,
    "last_modified": "Sat, 07 Mar 2020 22:34:01 GMT"
  },
  {
    "file_name": "photo-1585000104474-acc6e995215d",
    "url": "https://images.unsplash.com/photo-1585000104474-acc6e995215d?ixlib=rb-1.2.1&q=80&fm=jpg&crop=entropy&cs=tinysrgb&w=1080&fit=max",
    "file_size": 135134,
    "last_modified": "Fri, 27 Mar 2020 09:49:17 GMT"
  },
  {
    "file_name": "photo-1584632669012-63192c08d244",
    "url": "https://images.unsplash.com/photo-1584632669012-63192c08d244?ixlib=rb-1.2.1&q=80&fm=jpg&crop=entropy&cs=tinysrgb&w=1080&fit=max",
    "file_size": 160876,
    "last_modified": "Tue, 24 Mar 2020 17:25:18 GMT"
  },
  {
    "file_name": "photo-1584930672859-b997464e7b5e",
    "url": "https://images.unsplash.com/photo-1584930672859-b997464e7b5e?ixlib=rb-1.2.1&q=80&fm=jpg&crop=entropy&cs=tinysrgb&w=1080&fit=max",
    "file_size": 257406,
    "last_modified": "Mon, 23 Mar 2020 02:31:22 GMT"
  },
  {
    "file_name": "photo-1585553841579-c9edf60db739",
    "url": "https://images.unsplash.com/photo-1585553841579-c9edf60db739?ixlib=rb-1.2.1&q=80&fm=jpg&crop=entropy&cs=tinysrgb&w=1080&fit=max",
    "file_size": 73952,
    "last_modified": "Mon, 30 Mar 2020 07:37:44 GMT"
  },
  {
    "file_name": "photo-1585441167231-61a9bf18632d",
    "url": "https://images.unsplash.com/photo-1585441167231-61a9bf18632d?ixlib=rb-1.2.1&q=80&fm=jpg&crop=entropy&cs=tinysrgb&w=1080&fit=max",
    "file_size": 446383,
    "last_modified": "Sun, 29 Mar 2020 00:23:09 GMT"
  },
  {
    "file_name": "photo-1584905066858-2a80e5b56c2e",
    "url": "https://images.unsplash.com/photo-1584905066858-2a80e5b56c2e?ixlib=rb-1.2.1&q=80&fm=jpg&crop=entropy&cs=tinysrgb&w=1080&fit=max",
    "file_size": 155999,
    "last_modified": "Sun, 22 Mar 2020 19:24:52 GMT"
  },
  {
    "file_name": "photo-1585567346064-d7bdc13f7057",
    "url": "https://images.unsplash.com/photo-1585567346064-d7bdc13f7057?ixlib=rb-1.2.1&q=80&fm=jpg&crop=entropy&cs=tinysrgb&w=1080&fit=max",
    "file_size": 193213,
    "last_modified": "Mon, 30 Mar 2020 11:24:40 GMT"
  },
  {
    "file_name": "photo-1584834135274-2e3f0deb8865",
    "url": "https://images.unsplash.com/photo-1584834135274-2e3f0deb8865?ixlib=rb-1.2.1&q=80&fm=jpg&crop=entropy&cs=tinysrgb&w=1080&fit=max",
    "file_size": 297806,
    "last_modified": "Sat, 21 Mar 2020 23:42:48 GMT"
  },
  {
    "file_name": "photo-1584556812952-905ffd0c611a",
    "url": "https://images.unsplash.com/photo-1584556812952-905ffd0c611a?ixlib=rb-1.2.1&q=80&fm=jpg&crop=entropy&cs=tinysrgb&w=1080&fit=max",
    "file_size": 68062,
    "last_modified": "Wed, 18 Mar 2020 18:40:52 GMT"
  },
  {
    "file_name": "photo-1584090890743-e3a50dae8ced",
    "url": "https://images.unsplash.com/photo-1584090890743-e3a50dae8ced?ixlib=rb-1.2.1&q=80&fm=jpg&crop=entropy&cs=tinysrgb&w=1080&fit=max",
    "file_size": 252744,
    "last_modified": "Fri, 13 Mar 2020 09:16:41 GMT"
  },
  {
    "file_name": "photo-1584533148323-37535272412a",
    "url": "https://images.unsplash.com/photo-1584533148323-37535272412a?ixlib=rb-1.2.1&q=80&fm=jpg&crop=entropy&cs=tinysrgb&w=1080&fit=max",
    "file_size": 238242,
    "last_modified": "Tue, 24 Mar 2020 03:23:46 GMT"
  },
  {
    "file_name": "photo-1585581933793-f89f42d7289f",
    "url": "https://images.unsplash.com/photo-1585581933793-f89f42d7289f?ixlib=rb-1.2.1&q=80&fm=jpg&crop=entropy&cs=tinysrgb&w=1080&fit=max",
    "file_size": 128131,
    "last_modified": "Mon, 30 Mar 2020 15:28:37 GMT"
  },
  {
    "file_name": "photo-1583946849584-cf9fc02ef0a7",
    "url": "https://images.unsplash.com/photo-1583946849584-cf9fc02ef0a7?ixlib=rb-1.2.1&q=80&fm=jpg&crop=entropy&cs=tinysrgb&w=1080&fit=max",
    "file_size": 313540,
    "last_modified": "Thu, 26 Mar 2020 13:06:05 GMT"
  },
  {
    "file_name": "photo-1584583295981-224404303e01",
    "url": "https://images.unsplash.com/photo-1584583295981-224404303e01?ixlib=rb-1.2.1&q=80&fm=jpg&crop=entropy&cs=tinysrgb&w=1080&fit=max",
    "file_size": 333788,
    "last_modified": "Wed, 25 Mar 2020 12:40:44 GMT"
  },
  {
    "file_name": "photo-1585022762780-b316ed8a5964",
    "url": "https://images.unsplash.com/photo-1585022762780-b316ed8a5964?ixlib=rb-1.2.1&q=80&fm=jpg&crop=entropy&cs=tinysrgb&w=1080&fit=max",
    "file_size": 411357,
    "last_modified": "Tue, 24 Mar 2020 18:07:08 GMT"
  },
  {
    "file_name": "photo-1583623733237-4d5764a9dc82",
    "url": "https://images.unsplash.com/photo-1583623733237-4d5764a9dc82?ixlib=rb-1.2.1&q=80&fm=jpg&crop=entropy&cs=tinysrgb&w=1080&fit=max",
    "file_size": 338221,
    "last_modified": "Mon, 30 Mar 2020 08:38:27 GMT"
  },
  {
    "file_name": "photo-1584162246791-bf68b448fd28",
    "url": "https://images.unsplash.com/photo-1584162246791-bf68b448fd28?ixlib=rb-1.2.1&q=80&fm=jpg&crop=entropy&cs=tinysrgb&w=1080&fit=max",
    "file_size": 154048,
    "last_modified": "Tue, 24 Mar 2020 20:09:56 GMT"
  },
  {
    "file_name": "photo-1584893751588-f403fe105c02",
    "url": "https://images.unsplash.com/photo-1584893751588-f403fe105c02?ixlib=rb-1.2.1&q=80&fm=jpg&crop=entropy&cs=tinysrgb&w=1080&fit=max",
    "file_size": 311423,
    "last_modified": "Sun, 22 Mar 2020 16:21:38 GMT"
  },
  {
    "file_name": "photo-1583080287945-de6d770fcdf4",
    "url": "https://images.unsplash.com/photo-1583080287945-de6d770fcdf4?ixlib=rb-1.2.1&q=80&fm=jpg&crop=entropy&cs=tinysrgb&w=1080&fit=max",
    "file_size": 165449,
    "last_modified": "Thu, 26 Mar 2020 02:25:05 GMT"
  },
  {
    "file_name": "photo-1584901354120-75d29e0640ad",
    "url": "https://images.unsplash.com/photo-1584901354120-75d29e0640ad?ixlib=rb-1.2.1&q=80&fm=jpg&crop=entropy&cs=tinysrgb&w=1080&fit=max",
    "file_size": 99953,
    "last_modified": "Sun, 22 Mar 2020 18:24:14 GMT"
  },
  {
    "file_name": "photo-1584931423308-5105db746e25",
    "url": "https://images.unsplash.com/photo-1584931423308-5105db746e25?ixlib=rb-1.2.1&q=80&fm=jpg&crop=entropy&cs=tinysrgb&w=1080&fit=max",
    "file_size": 98811,
    "last_modified": "Mon, 23 Mar 2020 02:45:49 GMT"
  },
  {
    "file_name": "photo-1583645870037-5efd7b1b2614",
    "url": "https://images.unsplash.com/photo-1583645870037-5efd7b1b2614?ixlib=rb-1.2.1&q=80&fm=jpg&crop=entropy&cs=tinysrgb&w=1080&fit=max",
    "file_size": 238882,
    "last_modified": "Sun, 22 Mar 2020 21:52:49 GMT"
  },
  {
    "file_name": "photo-1584910643800-540e9e31ce32",
    "url": "https://images.unsplash.com/photo-1584910643800-540e9e31ce32?ixlib=rb-1.2.1&q=80&fm=jpg&crop=entropy&cs=tinysrgb&w=1080&fit=max",
    "file_size": 202597,
    "last_modified": "Sun, 22 Mar 2020 20:59:34 GMT"
  },
  {
    "file_name": "photo-1585163218247-7a44236dd0f5",
    "url": "https://images.unsplash.com/photo-1585163218247-7a44236dd0f5?ixlib=rb-1.2.1&q=80&fm=jpg&crop=entropy&cs=tinysrgb&w=1080&fit=max",
    "file_size": 204306,
    "last_modified": "Wed, 25 Mar 2020 19:09:07 GMT"
  },
  {
    "file_name": "photo-1584732977276-4ce5ed52576d",
    "url": "https://images.unsplash.com/photo-1584732977276-4ce5ed52576d?ixlib=rb-1.2.1&q=80&fm=jpg&crop=entropy&cs=tinysrgb&w=1080&fit=max",
    "file_size": 276965,
    "last_modified": "Fri, 20 Mar 2020 19:41:16 GMT"
  },
  {
    "file_name": "photo-1583743100126-a7bdb54a8930",
    "url": "https://images.unsplash.com/photo-1583743100126-a7bdb54a8930?ixlib=rb-1.2.1&q=80&fm=jpg&crop=entropy&cs=tinysrgb&w=1080&fit=max",
    "file_size": 213076,
    "last_modified": "Mon, 30 Mar 2020 07:51:29 GMT"
  },
  {
    "file_name": "photo-1583748531666-365bf8d287bb",
    "url": "https://images.unsplash.com/photo-1583748531666-365bf8d287bb?ixlib=rb-1.2.1&q=80&fm=jpg&crop=entropy&cs=tinysrgb&w=1080&fit=max",
    "file_size": 282179,
    "last_modified": "Fri, 20 Mar 2020 05:48:48 GMT"
  },
  {
    "file_name": "photo-1584722064979-691a48d229a5",
    "url": "https://images.unsplash.com/photo-1584722064979-691a48d229a5?ixlib=rb-1.2.1&q=80&fm=jpg&crop=entropy&cs=tinysrgb&w=1080&fit=max",
    "file_size": 236478,
    "last_modified": "Fri, 20 Mar 2020 16:34:44 GMT"
  },
  {
    "file_name": "photo-1584262790409-33f83747ee9e",
    "url": "https://images.unsplash.com/photo-1584262790409-33f83747ee9e?ixlib=rb-1.2.1&q=80&fm=jpg&crop=entropy&cs=tinysrgb&w=1080&fit=max",
    "file_size": 132010,
    "last_modified": "Sun, 15 Mar 2020 09:00:28 GMT"
  },
  {
    "file_name": "photo-1583373279496-3d839b4261c8",
    "url": "https://images.unsplash.com/photo-1583373279496-3d839b4261c8?ixlib=rb-1.2.1&q=80&fm=jpg&crop=entropy&cs=tinysrgb&w=1080&fit=max",
    "file_size": 149963,
    "last_modified": "Tue, 31 Mar 2020 04:20:52 GMT"
  },
  {
    "file_name": "photo-1583190791269-d9ab03272700",
    "url": "https://images.unsplash.com/photo-1583190791269-d9ab03272700?ixlib=rb-1.2.1&q=80&fm=jpg&crop=entropy&cs=tinysrgb&w=1080&fit=max",
    "file_size": 444148,
    "last_modified": "Tue, 24 Mar 2020 02:53:18 GMT"
  },
  {
    "file_name": "photo-1583943604115-bb69c7a7e191",
    "url": "https://images.unsplash.com/photo-1583943604115-bb69c7a7e191?ixlib=rb-1.2.1&q=80&fm=jpg&crop=entropy&cs=tinysrgb&w=1080&fit=max",
    "file_size": 224740,
    "last_modified": "Fri, 27 Mar 2020 11:47:15 GMT"
  },
  {
    "file_name": "photo-1583870996776-847fa9899398",
    "url": "https://images.unsplash.com/photo-1583870996776-847fa9899398?ixlib=rb-1.2.1&q=80&fm=jpg&crop=entropy&cs=tinysrgb&w=1080&fit=max",
    "file_size": 105824,
    "last_modified": "Tue, 24 Mar 2020 13:24:23 GMT"
  },
  {
    "file_name": "photo-1583492399408-6bf2a17cabe3",
    "url": "https://images.unsplash.com/photo-1583492399408-6bf2a17cabe3?ixlib=rb-1.2.1&q=80&fm=jpg&crop=entropy&cs=tinysrgb&w=1080&fit=max",
    "file_size": 295797,
    "last_modified": "Thu, 19 Mar 2020 13:33:31 GMT"
  },
  {
    "file_name": "photo-1583955967842-14dd8d6b8257",
    "url": "https://images.unsplash.com/photo-1583955967842-14dd8d6b8257?ixlib=rb-1.2.1&q=80&fm=jpg&crop=entropy&cs=tinysrgb&w=1080&fit=max",
    "file_size": 146246,
    "last_modified": "Mon, 23 Mar 2020 09:11:24 GMT"
  },
  {
    "file_name": "photo-1584986394904-e9b75328be93",
    "url": "https://images.unsplash.com/photo-1584986394904-e9b75328be93?ixlib=rb-1.2.1&q=80&fm=jpg&crop=entropy&cs=tinysrgb&w=1080&fit=max",
    "file_size": 129511,
    "last_modified": "Mon, 23 Mar 2020 18:00:12 GMT"
  },
  {
    "file_name": "photo-1583996169985-f8c9317a1029",
    "url": "https://images.unsplash.com/photo-1583996169985-f8c9317a1029?ixlib=rb-1.2.1&q=80&fm=jpg&crop=entropy&cs=tinysrgb&w=1080&fit=max",
    "file_size": 174861,
    "last_modified": "Thu, 12 Mar 2020 07:09:00 GMT"
  },
  {
    "file_name": "photo-1585585787219-32ba7df3c965",
    "url": "https://images.unsplash.com/photo-1585585787219-32ba7df3c965?ixlib=rb-1.2.1&q=80&fm=jpg&crop=entropy&cs=tinysrgb&w=1080&fit=max",
    "file_size": 88829,
    "last_modified": "Mon, 30 Mar 2020 16:44:48 GMT"
  },
  {
    "file_name": "photo-1585126521859-9677a3effd9e",
    "url": "https://images.unsplash.com/photo-1585126521859-9677a3effd9e?ixlib=rb-1.2.1&q=80&fm=jpg&crop=entropy&cs=tinysrgb&w=1080&fit=max",
    "file_size": 165442,
    "last_modified": "Wed, 25 Mar 2020 08:56:12 GMT"
  },
  {
    "file_name": "photo-1584995878285-cd14c962b1db",
    "url": "https://images.unsplash.com/photo-1584995878285-cd14c962b1db?ixlib=rb-1.2.1&q=80&fm=jpg&crop=entropy&cs=tinysrgb&w=1080&fit=max",
    "file_size": 316576,
    "last_modified": "Mon, 23 Mar 2020 20:46:28 GMT"
  },
  {
    "file_name": "photo-1584727618540-29833346de4b",
    "url": "https://images.unsplash.com/photo-1584727618540-29833346de4b?ixlib=rb-1.2.1&q=80&fm=jpg&crop=entropy&cs=tinysrgb&w=1080&fit=max",
    "file_size": 432392,
    "last_modified": "Fri, 20 Mar 2020 18:07:52 GMT"
  },
  {
    "file_name": "photo-1584610287147-c4b6770b764b",
    "url": "https://images.unsplash.com/photo-1584610287147-c4b6770b764b?ixlib=rb-1.2.1&q=80&fm=jpg&crop=entropy&cs=tinysrgb&w=1080&fit=max",
    "file_size": 167291,
    "last_modified": "Thu, 19 Mar 2020 09:33:26 GMT"
  },
  {
    "file_name": "photo-1583162086153-7bac86575393",
    "url": "https://images.unsplash.com/photo-1583162086153-7bac86575393?ixlib=rb-1.2.1&q=80&fm=jpg&crop=entropy&cs=tinysrgb&w=1080&fit=max",
    "file_size": 148870,
    "last_modified": "Fri, 27 Mar 2020 15:50:39 GMT"
  },
  {
    "file_name": "photo-1585040235386-e295239c0419",
    "url": "https://images.unsplash.com/photo-1585040235386-e295239c0419?ixlib=rb-1.2.1&q=80&fm=jpg&crop=entropy&cs=tinysrgb&w=1080&fit=max",
    "file_size": 156630,
    "last_modified": "Tue, 24 Mar 2020 09:08:09 GMT"
  },
  {
    "file_name": "photo-1584762470869-8ee9b8aaa868",
    "url": "https://images.unsplash.com/photo-1584762470869-8ee9b8aaa868?ixlib=rb-1.2.1&q=80&fm=jpg&crop=entropy&cs=tinysrgb&w=1080&fit=max",
    "file_size": 293128,
    "last_modified": "Sat, 21 Mar 2020 03:48:47 GMT"
  },
  {
    "file_name": "photo-1585250133075-e134d50e4abb",
    "url": "https://images.unsplash.com/photo-1585250133075-e134d50e4abb?ixlib=rb-1.2.1&q=80&fm=jpg&crop=entropy&cs=tinysrgb&w=1080&fit=max",
    "file_size": 145981,
    "last_modified": "Thu, 26 Mar 2020 19:17:33 GMT"
  },
  {
    "file_name": "photo-1585073318999-a83ee550a939",
    "url": "https://images.unsplash.com/photo-1585073318999-a83ee550a939?ixlib=rb-1.2.1&q=80&fm=jpg&crop=entropy&cs=tinysrgb&w=1080&fit=max",
    "file_size": 286316,
    "last_modified": "Tue, 24 Mar 2020 18:08:50 GMT"
  },
  {
    "file_name": "photo-1583163567997-77b04e6c5b24",
    "url": "https://images.unsplash.com/photo-1583163567997-77b04e6c5b24?ixlib=rb-1.2.1&q=80&fm=jpg&crop=entropy&cs=tinysrgb&w=1080&fit=max",
    "file_size": 138801,
    "last_modified": "Mon, 23 Mar 2020 08:45:23 GMT"
  },
  {
    "file_name": "photo-1583686543381-2608547b3963",
    "url": "https://images.unsplash.com/photo-1583686543381-2608547b3963?ixlib=rb-1.2.1&q=80&fm=jpg&crop=entropy&cs=tinysrgb&w=1080&fit=max",
    "file_size": 314857,
    "last_modified": "Sun, 08 Mar 2020 16:56:31 GMT"
  },
  {
    "file_name": "photo-1583081425553-8368b299d01a",
    "url": "https://images.unsplash.com/photo-1583081425553-8368b299d01a?ixlib=rb-1.2.1&q=80&fm=jpg&crop=entropy&cs=tinysrgb&w=1080&fit=max",
    "file_size": 157206,
    "last_modified": "Sun, 01 Mar 2020 17:16:00 GMT"
  },
  {
    "file_name": "photo-1584990265011-35ec3b690846",
    "url": "https://images.unsplash.com/photo-1584990265011-35ec3b690846?ixlib=rb-1.2.1&q=80&fm=jpg&crop=entropy&cs=tinysrgb&w=1080&fit=max",
    "file_size": 290777,
    "last_modified": "Mon, 23 Mar 2020 19:04:50 GMT"
  },
  {
    "file_name": "photo-1584481119735-d694edceffa1",
    "url": "https://images.unsplash.com/photo-1584481119735-d694edceffa1?ixlib=rb-1.2.1&q=80&fm=jpg&crop=entropy&cs=tinysrgb&w=1080&fit=max",
    "file_size": 280494,
    "last_modified": "Tue, 17 Mar 2020 21:41:09 GMT"
  },
  {
    "file_name": "photo-1584589167171-541ce45f1eea",
    "url": "https://images.unsplash.com/photo-1584589167171-541ce45f1eea?ixlib=rb-1.2.1&q=80&fm=jpg&crop=entropy&cs=tinysrgb&w=1080&fit=max",
    "file_size": 89523,
    "last_modified": "Thu, 19 Mar 2020 03:40:20 GMT"
  },
  {
    "file_name": "photo-1584315296878-37b5bcdd6bc5",
    "url": "https://images.unsplash.com/photo-1584315296878-37b5bcdd6bc5?ixlib=rb-1.2.1&q=80&fm=jpg&crop=entropy&cs=tinysrgb&w=1080&fit=max",
    "file_size": 131452,
    "last_modified": "Sun, 15 Mar 2020 23:35:39 GMT"
  },
  {
    "file_name": "photo-1584455809483-acbb29b048c5",
    "url": "https://images.unsplash.com/photo-1584455809483-acbb29b048c5?ixlib=rb-1.2.1&q=80&fm=jpg&crop=entropy&cs=tinysrgb&w=1080&fit=max",
    "file_size": 202326,
    "last_modified": "Tue, 17 Mar 2020 14:40:23 GMT"
  },
  {
    "file_name": "photo-1584822637328-52c834e23a42",
    "url": "https://images.unsplash.com/photo-1584822637328-52c834e23a42?ixlib=rb-1.2.1&q=80&fm=jpg&crop=entropy&cs=tinysrgb&w=1080&fit=max",
    "file_size": 113519,
    "last_modified": "Sat, 21 Mar 2020 20:31:20 GMT"
  },
  {
    "file_name": "photo-1583356754293-334a37009248",
    "url": "https://images.unsplash.com/photo-1583356754293-334a37009248?ixlib=rb-1.2.1&q=80&fm=jpg&crop=entropy&cs=tinysrgb&w=1080&fit=max",
    "file_size": 204752,
    "last_modified": "Sun, 29 Mar 2020 05:27:01 GMT"
  },
  {
    "file_name": "photo-1584587358798-c9f4b1400e48",
    "url": "https://images.unsplash.com/photo-1584587358798-c9f4b1400e48?ixlib=rb-1.2.1&q=80&fm=jpg&crop=entropy&cs=tinysrgb&w=1080&fit=max",
    "file_size": 92394,
    "last_modified": "Thu, 19 Mar 2020 03:10:22 GMT"
  },
  {
    "file_name": "photo-1584722065001-ee7f49d903b1",
    "url": "https://images.unsplash.com/photo-1584722065001-ee7f49d903b1?ixlib=rb-1.2.1&q=80&fm=jpg&crop=entropy&cs=tinysrgb&w=1080&fit=max",
    "file_size": 112812,
    "last_modified": "Fri, 20 Mar 2020 16:34:44 GMT"
  },
  {
    "file_name": "photo-1583659736635-eaceb687bd2a",
    "url": "https://images.unsplash.com/photo-1583659736635-eaceb687bd2a?ixlib=rb-1.2.1&q=80&fm=jpg&crop=entropy&cs=tinysrgb&w=1080&fit=max",
    "file_size": 93296,
    "last_modified": "Tue, 24 Mar 2020 11:45:35 GMT"
  },
  {
    "file_name": "photo-1583253029513-710c8edbcecf",
    "url": "https://images.unsplash.com/photo-1583253029513-710c8edbcecf?ixlib=rb-1.2.1&q=80&fm=jpg&crop=entropy&cs=tinysrgb&w=1080&fit=max",
    "file_size": 423752,
    "last_modified": "Tue, 03 Mar 2020 16:30:50 GMT"
  },
  {
    "file_name": "photo-1583356051651-ff8586e2a9c1",
    "url": "https://images.unsplash.com/photo-1583356051651-ff8586e2a9c1?ixlib=rb-1.2.1&q=80&fm=jpg&crop=entropy&cs=tinysrgb&w=1080&fit=max",
    "file_size": 256712,
    "last_modified": "Wed, 04 Mar 2020 21:08:41 GMT"
  },
  {
    "file_name": "photo-1585440866327-5c59ff8c4c96",
    "url": "https://images.unsplash.com/photo-1585440866327-5c59ff8c4c96?ixlib=rb-1.2.1&q=80&fm=jpg&crop=entropy&cs=tinysrgb&w=1080&fit=max",
    "file_size": 276044,
    "last_modified": "Sun, 29 Mar 2020 00:15:30 GMT"
  },
  {
    "file_name": "photo-1584735935682-2f2b69dff9d2",
    "url": "https://images.unsplash.com/photo-1584735935682-2f2b69dff9d2?ixlib=rb-1.2.1&q=80&fm=jpg&crop=entropy&cs=tinysrgb&w=1080&fit=max",
    "file_size": 201632,
    "last_modified": "Fri, 20 Mar 2020 20:26:19 GMT"
  },
  {
    "file_name": "photo-1584545251997-b4f7ae63911c",
    "url": "https://images.unsplash.com/photo-1584545251997-b4f7ae63911c?ixlib=rb-1.2.1&q=80&fm=jpg&crop=entropy&cs=tinysrgb&w=1080&fit=max",
    "file_size": 147589,
    "last_modified": "Wed, 25 Mar 2020 16:45:17 GMT"
  },
  {
    "file_name": "photo-1583710071423-70eac8a6cf6f",
    "url": "https://images.unsplash.com/photo-1583710071423-70eac8a6cf6f?ixlib=rb-1.2.1&q=80&fm=jpg&crop=entropy&cs=tinysrgb&w=1080&fit=max",
    "file_size": 352876,
    "last_modified": "Thu, 26 Mar 2020 04:57:39 GMT"
  },
  {
    "file_name": "photo-1583127667348-22da6d3165b8",
    "url": "https://images.unsplash.com/photo-1583127667348-22da6d3165b8?ixlib=rb-1.2.1&q=80&fm=jpg&crop=entropy&cs=tinysrgb&w=1080&fit=max",
    "file_size": 100747,
    "last_modified": "Wed, 18 Mar 2020 11:32:11 GMT"
  },
  {
    "file_name": "photo-1583133183518-afdcfc27ef24",
    "url": "https://images.unsplash.com/photo-1583133183518-afdcfc27ef24?ixlib=rb-1.2.1&q=80&fm=jpg&crop=entropy&cs=tinysrgb&w=1080&fit=max",
    "file_size": 321630,
    "last_modified": "Thu, 12 Mar 2020 11:44:08 GMT"
  },
  {
    "file_name": "photo-1584532487395-d3f2b8174c2f",
    "url": "https://images.unsplash.com/photo-1584532487395-d3f2b8174c2f?ixlib=rb-1.2.1&q=80&fm=jpg&crop=entropy&cs=tinysrgb&w=1080&fit=max",
    "file_size": 179165,
    "last_modified": "Wed, 18 Mar 2020 11:55:46 GMT"
  },
  {
    "file_name": "photo-1583975956249-28c627731ffc",
    "url": "https://images.unsplash.com/photo-1583975956249-28c627731ffc?ixlib=rb-1.2.1&q=80&fm=jpg&crop=entropy&cs=tinysrgb&w=1080&fit=max",
    "file_size": 103068,
    "last_modified": "Thu, 12 Mar 2020 01:19:30 GMT"
  },
  {
    "file_name": "photo-1583541005680-18a87086e89d",
    "url": "https://images.unsplash.com/photo-1583541005680-18a87086e89d?ixlib=rb-1.2.1&q=80&fm=jpg&crop=entropy&cs=tinysrgb&w=1080&fit=max",
    "file_size": 162143,
    "last_modified": "Fri, 27 Mar 2020 20:50:43 GMT"
  },
  {
    "file_name": "photo-1585354914593-cef5e545f836",
    "url": "https://images.unsplash.com/photo-1585354914593-cef5e545f836?ixlib=rb-1.2.1&q=80&fm=jpg&crop=entropy&cs=tinysrgb&w=1080&fit=max",
    "file_size": 72539,
    "last_modified": "Sat, 28 Mar 2020 00:37:24 GMT"
  },
  {
    "file_name": "photo-1583761765905-6bd543ceb1c6",
    "url": "https://images.unsplash.com/photo-1583761765905-6bd543ceb1c6?ixlib=rb-1.2.1&q=80&fm=jpg&crop=entropy&cs=tinysrgb&w=1080&fit=max",
    "file_size": 311451,
    "last_modified": "Tue, 17 Mar 2020 09:21:00 GMT"
  },
  {
    "file_name": "photo-1584278423161-2de6ed21f616",
    "url": "https://images.unsplash.com/photo-1584278423161-2de6ed21f616?ixlib=rb-1.2.1&q=80&fm=jpg&crop=entropy&cs=tinysrgb&w=1080&fit=max",
    "file_size": 379180,
    "last_modified": "Sun, 15 Mar 2020 13:39:00 GMT"
  },
  {
    "file_name": "photo-1585602173558-723c457c2454",
    "url": "https://images.unsplash.com/photo-1585602173558-723c457c2454?ixlib=rb-1.2.1&q=80&fm=jpg&crop=entropy&cs=tinysrgb&w=1080&fit=max",
    "file_size": 279704,
    "last_modified": "Mon, 30 Mar 2020 21:03:11 GMT"
  },
  {
    "file_name": "photo-1584138966995-f4cbdfc36bbb",
    "url": "https://images.unsplash.com/photo-1584138966995-f4cbdfc36bbb?ixlib=rb-1.2.1&q=80&fm=jpg&crop=entropy&cs=tinysrgb&w=1080&fit=max",
    "file_size": 202834,
    "last_modified": "Wed, 25 Mar 2020 08:16:07 GMT"
  },
  {
    "file_name": "photo-1583597975730-c0eece0096cc",
    "url": "https://images.unsplash.com/photo-1583597975730-c0eece0096cc?ixlib=rb-1.2.1&q=80&fm=jpg&crop=entropy&cs=tinysrgb&w=1080&fit=max",
    "file_size": 252522,
    "last_modified": "Fri, 27 Mar 2020 03:40:28 GMT"
  },
  {
    "file_name": "photo-1585509875364-39df877cd225",
    "url": "https://images.unsplash.com/photo-1585509875364-39df877cd225?ixlib=rb-1.2.1&q=80&fm=jpg&crop=entropy&cs=tinysrgb&w=1080&fit=max",
    "file_size": 115624,
    "last_modified": "Sun, 29 Mar 2020 19:27:14 GMT"
  },
  {
    "file_name": "photo-1585194743875-284e846e65da",
    "url": "https://images.unsplash.com/photo-1585194743875-284e846e65da?ixlib=rb-1.2.1&q=80&fm=jpg&crop=entropy&cs=tinysrgb&w=1080&fit=max",
    "file_size": 391696,
    "last_modified": "Thu, 26 Mar 2020 03:56:37 GMT"
  },
  {
    "file_name": "photo-1584720223124-466ff369e7c2",
    "url": "https://images.unsplash.com/photo-1584720223124-466ff369e7c2?ixlib=rb-1.2.1&q=80&fm=jpg&crop=entropy&cs=tinysrgb&w=1080&fit=max",
    "file_size": 152160,
    "last_modified": "Fri, 20 Mar 2020 16:03:53 GMT"
  },
  {
    "file_name": "photo-1583183634411-47514a69722c",
    "url": "https://images.unsplash.com/photo-1583183634411-47514a69722c?ixlib=rb-1.2.1&q=80&fm=jpg&crop=entropy&cs=tinysrgb&w=1080&fit=max",
    "file_size": 126497,
    "last_modified": "Sat, 07 Mar 2020 18:58:13 GMT"
  },
  {
    "file_name": "photo-1584316384360-365d7de77e5b",
    "url": "https://images.unsplash.com/photo-1584316384360-365d7de77e5b?ixlib=rb-1.2.1&q=80&fm=jpg&crop=entropy&cs=tinysrgb&w=1080&fit=max",
    "file_size": 164630,
    "last_modified": "Mon, 30 Mar 2020 07:31:45 GMT"
  },
  {
    "file_name": "photo-1583355261087-0d6c861a946a",
    "url": "https://images.unsplash.com/photo-1583355261087-0d6c861a946a?ixlib=rb-1.2.1&q=80&fm=jpg&crop=entropy&cs=tinysrgb&w=1080&fit=max",
    "file_size": 199911,
    "last_modified": "Sun, 29 Mar 2020 08:34:54 GMT"
  },
  {
    "file_name": "photo-1585144570627-aa9de0f47f71",
    "url": "https://images.unsplash.com/photo-1585144570627-aa9de0f47f71?ixlib=rb-1.2.1&q=80&fm=jpg&crop=entropy&cs=tinysrgb&w=1080&fit=max",
    "file_size": 183938,
    "last_modified": "Wed, 25 Mar 2020 13:58:18 GMT"
  },
  {
    "file_name": "photo-1585504792289-44440692fefa",
    "url": "https://images.unsplash.com/photo-1585504792289-44440692fefa?ixlib=rb-1.2.1&q=80&fm=jpg&crop=entropy&cs=tinysrgb&w=1080&fit=max",
    "file_size": 357393,
    "last_modified": "Sun, 29 Mar 2020 18:00:28 GMT"
  },
  {
    "file_name": "photo-1583748493291-7938f0657681",
    "url": "https://images.unsplash.com/photo-1583748493291-7938f0657681?ixlib=rb-1.2.1&q=80&fm=jpg&crop=entropy&cs=tinysrgb&w=1080&fit=max",
    "file_size": 207709,
    "last_modified": "Sun, 29 Mar 2020 19:47:50 GMT"
  },
  {
    "file_name": "photo-1584486921852-9235e8f57ba9",
    "url": "https://images.unsplash.com/photo-1584486921852-9235e8f57ba9?ixlib=rb-1.2.1&q=80&fm=jpg&crop=entropy&cs=tinysrgb&w=1080&fit=max",
    "file_size": 136589,
    "last_modified": "Fri, 27 Mar 2020 00:07:40 GMT"
  },
  {
    "file_name": "photo-1584270845190-c371857dc5dc",
    "url": "https://images.unsplash.com/photo-1584270845190-c371857dc5dc?ixlib=rb-1.2.1&q=80&fm=jpg&crop=entropy&cs=tinysrgb&w=1080&fit=max",
    "file_size": 116476,
    "last_modified": "Sat, 21 Mar 2020 17:23:47 GMT"
  },
  {
    "file_name": "photo-1584247740245-23dfe7d9a125",
    "url": "https://images.unsplash.com/photo-1584247740245-23dfe7d9a125?ixlib=rb-1.2.1&q=80&fm=jpg&crop=entropy&cs=tinysrgb&w=1080&fit=max",
    "file_size": 187477,
    "last_modified": "Sat, 21 Mar 2020 01:50:23 GMT"
  },
  {
    "file_name": "photo-1583585635793-0e1894c169bd",
    "url": "https://images.unsplash.com/photo-1583585635793-0e1894c169bd?ixlib=rb-1.2.1&q=80&fm=jpg&crop=entropy&cs=tinysrgb&w=1080&fit=max",
    "file_size": 96997,
    "last_modified": "Sat, 07 Mar 2020 12:54:27 GMT"
  },
  {
    "file_name": "photo-1583166377935-307886e5ae55",
    "url": "https://images.unsplash.com/photo-1583166377935-307886e5ae55?ixlib=rb-1.2.1&q=80&fm=jpg&crop=entropy&cs=tinysrgb&w=1080&fit=max",
    "file_size": 91213,
    "last_modified": "Mon, 02 Mar 2020 16:28:18 GMT"
  },
  {
    "file_name": "photo-1584308685190-c6cc1ec0249d",
    "url": "https://images.unsplash.com/photo-1584308685190-c6cc1ec0249d?ixlib=rb-1.2.1&q=80&fm=jpg&crop=entropy&cs=tinysrgb&w=1080&fit=max",
    "file_size": 82150,
    "last_modified": "Sun, 29 Mar 2020 12:28:03 GMT"
  },
  {
    "file_name": "photo-1583808547790-fb0268e3f29f",
    "url": "https://images.unsplash.com/photo-1583808547790-fb0268e3f29f?ixlib=rb-1.2.1&q=80&fm=jpg&crop=entropy&cs=tinysrgb&w=1080&fit=max",
    "file_size": 124325,
    "last_modified": "Tue, 10 Mar 2020 02:50:47 GMT"
  },
  {
    "file_name": "photo-1585068294277-b408285aee4a",
    "url": "https://images.unsplash.com/photo-1585068294277-b408285aee4a?ixlib=rb-1.2.1&q=80&fm=jpg&crop=entropy&cs=tinysrgb&w=1080&fit=max",
    "file_size": 185431,
    "last_modified": "Tue, 24 Mar 2020 16:46:31 GMT"
  },
  {
    "file_name": "photo-1585254415433-93cce01204f2",
    "url": "https://images.unsplash.com/photo-1585254415433-93cce01204f2?ixlib=rb-1.2.1&q=80&fm=jpg&crop=entropy&cs=tinysrgb&w=1080&fit=max",
    "file_size": 78938,
    "last_modified": "Thu, 26 Mar 2020 20:28:10 GMT"
  },
  {
    "file_name": "photo-1584203807086-eaab88d04680",
    "url": "https://images.unsplash.com/photo-1584203807086-eaab88d04680?ixlib=rb-1.2.1&q=80&fm=jpg&crop=entropy&cs=tinysrgb&w=1080&fit=max",
    "file_size": 68999,
    "last_modified": "Sat, 14 Mar 2020 16:37:54 GMT"
  },
  {
    "file_name": "photo-1584289135692-d5e5e4574864",
    "url": "https://images.unsplash.com/photo-1584289135692-d5e5e4574864?ixlib=rb-1.2.1&q=80&fm=jpg&crop=entropy&cs=tinysrgb&w=1080&fit=max",
    "file_size": 327714,
    "last_modified": "Mon, 30 Mar 2020 16:08:57 GMT"
  },
  {
    "file_name": "photo-1584593744985-ec3ff147b2a3",
    "url": "https://images.unsplash.com/photo-1584593744985-ec3ff147b2a3?ixlib=rb-1.2.1&q=80&fm=jpg&crop=entropy&cs=tinysrgb&w=1080&fit=max",
    "file_size": 333237,
    "last_modified": "Fri, 27 Mar 2020 10:56:06 GMT"
  },
  {
    "file_name": "photo-1584906248879-6cd5ea1eb911",
    "url": "https://images.unsplash.com/photo-1584906248879-6cd5ea1eb911?ixlib=rb-1.2.1&q=80&fm=jpg&crop=entropy&cs=tinysrgb&w=1080&fit=max",
    "file_size": 162740,
    "last_modified": "Sun, 22 Mar 2020 19:44:58 GMT"
  }
]